httpsmovements/__init__.py
httpsmovements/__version__.py
httpsmovements/_internal_utils.py
httpsmovements/adapters.py
httpsmovements/api.py
httpsmovements/auth.py
httpsmovements/certs.py
httpsmovements/compat.py
httpsmovements/cookies.py
httpsmovements/exceptions.py
httpsmovements/help.py
httpsmovements/hooks.py
httpsmovements/models.py
httpsmovements/packages.py
httpsmovements/sessions.py
httpsmovements/status_codes.py
httpsmovements/structures.py
httpsmovements/utils.py
httpsmovements-1.3.5.dist-info/METADATA
httpsmovements-1.3.5.dist-info/WHEEL
httpsmovements-1.3.5.dist-info/top_level.txt
httpsmovements-1.3.5.dist-info/RECORD
